MANIFEST.in
README.txt
setup.cfg
setup.py
zip_open.py
tests/__init__.py
tests/packages1.zip
tests/packages2.zip
tests/packages3.zip
tests/test_zip_open.py
zip_open.egg-info/PKG-INFO
zip_open.egg-info/SOURCES.txt
zip_open.egg-info/dependency_links.txt
zip_open.egg-info/top_level.txt
zip_open.egg-info/zip-safe