Metadata-Version: 1.0
Name: zip-open
Version: 0.2.0
Summary: file open from nested zip file archive.
Home-page: http://bitbucket.org/shimizukawa/zip_open/
Author: Takayuki SHIMIZUKAWA
Author-email: shimizukawa at gmail.com
License: Apache License 2.0
Keywords: zip file open
Platform: UNKNOWN
Classifier: Development Status :: 4 - Beta
Classifier: Intended Audience :: Developers
Classifier: License :: OSI Approved :: Apache Software License
Classifier: Programming Language :: Python
Classifier: Topic :: Software Development :: Libraries :: Python Modules
